manafa/__init__.py
manafa/emanafa.py
manafa/batteryStats/BatteryStatsConstants.py
manafa/batteryStats/BatteryStatsParser.py
manafa/batteryStats/__init__.py
manafa/perfetto/__init__.py
manafa/perfetto/perfettoParser.py
manafa/powerProfile/PowerProfile.py
manafa/powerProfile/__init__.py
manafa/services/__init__.py
manafa/services/batteryStatsService.py
manafa/services/perfettoService.py
manafa/services/service.py
manafa/utils/Logger.py
manafa/utils/Utils.py
manafa/utils/__init__.py
manafa/utils/dateUtils.py
tests/__init__.py
tests/batterystats/__init__.py
tests/batterystats/test_batteryStatsService.py
tests/perfetto/__init__.py
tests/perfetto/test_perfettoService.py
manafa-0.2.1.dist-info/METADATA
manafa-0.2.1.dist-info/WHEEL
manafa-0.2.1.dist-info/top_level.txt
manafa-0.2.1.dist-info/RECORD
