Metadata-Version: 2.1
Name: manafa
Version: 0.2.1
Summary: E-MANAFA: Energy Monitor and ANAlyzer For Android
Home-page: https://github.com/RRua/e-manafa
Author: Rui Rua
Author-email: rui.rrua@gmail.com
License: MIT
Project-URL: Bug Tracker, https://github.com/RRua/e-manafa/issues
Platform: UNKNOWN
Classifier: License :: OSI Approved :: MIT License
Classifier: Intended Audience :: Science/Research
Classifier: Operating System :: OS Independent
Classifier: Programming Language :: Python :: 3.8
Requires-Python: >=3.8
Requires-Dist: pytz (==2021.1)
Requires-Dist: termcolor (==1.1.0)
Requires-Dist: python-textops3 (==3.1.0)
Requires-Dist: python-dateutil (==2.8.1)
Requires-Dist: setuptools (>=42)
Requires-Dist: wheel
